first_part/multiplexer/multiplexer_2_1_ternary_operator.sv
module multiplexer_2_1_ternary_operator (
    input  logic IN0,
    input  logic IN1,
    input  logic SEL,

    output logic OUT
);

    assign OUT = SEL ? IN1 : IN0;

endmodule

first_part/multiplexer/multiplexer_2_1_case.sv
module multiplexer_2_1_case (
    input  logic IN0,
    input  logic IN1,
    input  logic SEL,

    output logic OUT
);

    always_comb begin
        case(SEL)
        0:       OUT = IN0;
        1:       OUT = IN1;
        default: OUT = 1'bx;
        endcase
    end

endmodule

1_first_part/multiplexer/multiplexer_2_1_if_else.sv
module multiplexer_2_1_if_else (
    input  logic IN0,
    input  logic IN1,
    input  logic SEL,

    output logic OUT
);

    always_comb begin
        if (SEL) OUT = IN1;
        else     OUT = IN0;
    end

endmodule

first_part/multiplexer/multiplexer_2_1_tb.sv
module multiplexer_2_1_tb;

logic IN0, IN1, SEL;

logic OUT_if_else;
logic OUT_case;
logic OUT_ternary_operator;

logic OUT_expected;

logic [3:0] count_if_else          = 0;
logic [3:0] count_case             = 0;
logic [3:0] count_ternary_operator = 0;

multiplexer_2_1_if_else inst_if_else (
    .IN0(IN0),
    .IN1(IN1),
    .SEL(SEL),
    .OUT(OUT_if_else)
);

multiplexer_2_1_case inst_case (
    .IN0(IN0),
    .IN1(IN1),
    .SEL(SEL),
    .OUT(OUT_case)
);

multiplexer_2_1_ternary_operator inst_ternary_operator (
    .IN0(IN0),
    .IN1(IN1),
    .SEL(SEL),
    .OUT(OUT_ternary_operator)
);

initial begin
    for (int sel = 0; sel <= 1; sel++) begin
        SEL = sel;
        for (int in0 = 0; in0 <= 1; in0++) begin
            IN0 = in0;
            for (int in1 = 0; in1 <= 1; in1++) begin
                IN1 = in1;

                #10;

                OUT_expected = (IN1 & SEL) | (IN0 & ~SEL);

                if (OUT_expected == OUT_if_else) count_if_else++;
                else $error("%b | %b | %b | %b | FAIL_if_else", SEL, IN0, IN1, OUT_if_else);

                if (OUT_expected == OUT_case) count_case++;
                else $error("%b | %b | %b | %b | FAIL_case", SEL, IN0, IN1, OUT_case);

                if (OUT_expected == OUT_ternary_operator) count_ternary_operator++;
                else $error("%b | %b | %b | %b | FAIL_ternary_operator", SEL, IN0, IN1, OUT_ternary_operator);

            end
        end
    end
    
    if (count_if_else == 8)             
        $display("multiplexer_2_1_if_else PASS");
    if (count_case == 8)                
        $display("multiplexer_2_1_case PASS");
    if (count_ternary_operator == 8)    
        $display("multiplexer_2_1_ternary_operator PASS");

$finish;
end

initial begin
    $dumpfile("multiplexer_2_1_timing_diagram.vcd");
    $dumpvars(0, multiplexer_2_1_tb);
end

endmodule

first_part/multiplexer/multiplexer_2_1_timing_diagram.vcd
$date
	Wed Oct 07 22:02:24 2026
$end
$version
	Icarus Verilog
$end
$timescale
	1s
$end
$scope module multiplexer_2_1_tb $end
$var wire 1 ! OUT_ternary_operator $end
$var wire 1 " OUT_if_else $end
$var wire 1 # OUT_case $end
$var reg 1 $ IN0 $end
$var reg 1 % IN1 $end
$var reg 1 & OUT_expected $end
$var reg 1 ' SEL $end
$var reg 4 ( count_case [3:0] $end
$var reg 4 ) count_if_else [3:0] $end
$var reg 4 * count_ternary_operator [3:0] $end
$scope module inst_case $end
$var wire 1 $ IN0 $end
$var wire 1 % IN1 $end
$var wire 1 ' SEL $end
$var reg 1 # OUT $end
$upscope $end
$scope module inst_if_else $end
$var wire 1 $ IN0 $end
$var wire 1 % IN1 $end
$var wire 1 ' SEL $end
$var reg 1 " OUT $end
$upscope $end
$scope module inst_ternary_operator $end
$var wire 1 $ IN0 $end
$var wire 1 % IN1 $end
$var wire 1 ' SEL $end
$var wire 1 ! OUT $end
$upscope $end
$scope begin $ivl_for_loop0 $end
$var integer 32 + sel [31:0] $end
$scope begin $ivl_for_loop1 $end
$var integer 32 , in0 [31:0] $end
$scope begin $ivl_for_loop2 $end
$var integer 32 - in1 [31:0] $end
$upscope $end
$upscope $end
$upscope $end
$upscope $end
$enddefinitions $end
$comment Show the parameter values. $end
$dumpall
$end
#0
$dumpvars
b0 -
b0 ,
b0 +
b0 *
b0 )
b0 (
0'
x&
0%
0$
0#
0"
0!
$end
#10
1%
b1 -
b1 *
b1 (
b1 )
0&
#20
1#
1"
1!
0%
1$
b1 ,
b0 -
b10 *
b10 (
b10 )
#30
1%
b1 -
b11 *
b11 (
b11 )
1&
#40
0#
0"
0!
0%
0$
1'
b1 +
b0 ,
b0 -
b100 *
b100 (
b100 )
#50
1#
1"
1!
1%
b1 -
b101 *
b101 (
b101 )
0&
#60
0!
0#
0"
0%
1$
b1 ,
b0 -
b110 *
b110 (
b110 )
1&
#70
1#
1"
1!
1%
b1 -
b111 *
b111 (
b111 )
0&
#80
b10 +
b10 ,
b10 -
b1000 *
b1000 (
b1000 )
1&
